cockup/__init__.py
cockup/main.py
cockup/src/__init__.py
cockup/src/backup.py
cockup/src/config.py
cockup/src/console.py
cockup/src/hooks.py
cockup/src/list.py
cockup/src/restore.py
cockup/src/rules.py
cockup-0.1.10.dist-info/licenses/LICENSE
cockup-0.1.10.dist-info/METADATA
cockup-0.1.10.dist-info/WHEEL
cockup-0.1.10.dist-info/entry_points.txt
cockup-0.1.10.dist-info/top_level.txt
cockup-0.1.10.dist-info/RECORD
