Metadata-Version: 2.4
Name: cockup
Version: 0.1.10
Summary: Yet another backup tool for various configurations
Author-email: huaium <huaium233@gmail.com>
License-Expression: MIT
Project-URL: Homepage, https://github.com/huaium/cockup
Project-URL: Repository, https://github.com/huaium/cockup
Project-URL: Issues, https://github.com/huaium/cockup/issues
Classifier: Development Status :: 4 - Beta
Classifier: Intended Audience :: Developers
Classifier: Programming Language :: Python :: 3
Classifier: Programming Language :: Python :: 3.13
Requires-Python: <3.14,>=3.13
License-File: LICENSE
Requires-Dist: PyYAML<6.1,>=6.0
Requires-Dist: termcolor<3.2,>=3.1
Requires-Dist: click<8.3,>=8.2
Provides-Extra: test
Requires-Dist: pytest<8.5,>=8.4; extra == "test"
Requires-Dist: pytest-cov<6.3,>=6.2; extra == "test"
Requires-Dist: pytest-mock<3.15,>=3.14; extra == "test"
Dynamic: license-file
